mangosteen/__init__.py
mangosteen/data_ui_model.py
mangosteen/jinja_cust_funcs.py
mangosteen/mangosteen_base.py
mangosteen/routes.py
mangosteen/static/zcss/debug.css
mangosteen/static/zcss/main.css
mangosteen/static/zjs/ajv7.js
mangosteen/static/zjs/common_utils.js
mangosteen/static/zjs/field_checker.js
mangosteen/static/zjs/validation_helper.js
mangosteen/static/zwc/wc_all.js
mangosteen/static/zwc/wc_button.js
mangosteen/static/zwc/wc_checkbox.js
mangosteen/static/zwc/wc_common_utils.js
mangosteen/static/zwc/wc_control_switch.js
mangosteen/static/zwc/wc_elt_parent.js
mangosteen/static/zwc/wc_form.js
mangosteen/static/zwc/wc_form_json.js
mangosteen/static/zwc/wc_group.js
mangosteen/static/zwc/wc_grp_parent.js
mangosteen/static/zwc/wc_hidden.js
mangosteen/static/zwc/wc_input.js
mangosteen/static/zwc/wc_message.js
mangosteen/static/zwc/wc_modal.js
mangosteen/static/zwc/wc_nav.js
mangosteen/static/zwc/wc_nav__inc__menu.js
mangosteen/static/zwc/wc_nav__inc__menu_action.js
mangosteen/static/zwc/wc_nav__inc__render_content_area.js
mangosteen/static/zwc/wc_nav__inc__render_menu.js
mangosteen/static/zwc/wc_persistent_dropdown.js
mangosteen/static/zwc/wc_radio.js
mangosteen/static/zwc/wc_root.js
mangosteen/static/zwc/wc_select.js
mangosteen/static/zwc/wc_side_panel.js
mangosteen/static/zwc/wc_tab.js
mangosteen/static/zwc/wc_table.js
mangosteen/static/zwc/wc_table_gui.js
mangosteen/static/zwc/wc_table_updater.js
mangosteen/web_field.py
mangosteen-0.1.0.dist-info/WHEEL
mangosteen-0.1.0.dist-info/METADATA
mangosteen-0.1.0.dist-info/RECORD
