Metadata-Version: 2.1
Name: mangosteen
Version: 0.1.0
Summary: Web widgets
Author: pub12
Author-email: pubudu79@gmail.com
Requires-Python: >=3.8,<4.0
Classifier: Programming Language :: Python :: 3
Classifier: Programming Language :: Python :: 3.10
Classifier: Programming Language :: Python :: 3.8
Classifier: Programming Language :: Python :: 3.9
Requires-Dist: json-cfg
Requires-Dist: pymongo
